Workbook
Name ins: Analysis!$C$35
Name young: Analysis!$A$11
Name freq: Analysis!$C$33
Name old: Analysis!$A$31
Name mid: Analysis!$A$21
Name exp: 'Raw Data'!$F$2

Sheet Raw Data
A1: gender | B1: age_group | C1: income_bracket | D1: uninsured_population | E1: total_population | F1: base_severity | I1: cumulative uninsured pop | J1: cumulative insured pop
A2: Male | B2: 18 to 64 years | C2: <= 138% of poverty | D2: 11598 | E2: 75033 | F2: 74403.06 | G2: Male | H2: <= 138% of poverty | I2: =IFERROR(__xludf.DUMMYFUNCTION("IFERROR(SUM(FILTER(D:D, A:A=G2, C:C=H2, B:B=""18 to 64 years"")), 0) - IFERROR(SUM(FILTER(D:D, A:A=G2, C:C=H2, B:B=""40 to 64 years"")), 0)"),6367.0) -> 6367 | J2: =IFERROR(__xludf.DUMMYFUNCTION("IFERROR(SUM(FILTER(E:E, A:A=G2, C:C=H2, B:B=""18 to 64 years"")), 0) - IFERROR(SUM(FILTER(E:E, A:A=G2, C:C=H2, B:B=""40 to 64 years"")), 0)"),41257.0) -> 41257 | K2: =I2/J2 -> 0.15432533 | L2: 18-40
A3: Male | B3: 18 to 64 years | C3: <= 200% poverty | D3: 19240 | E3: 120330 | F3: 74403.06 | G3: Male | H3: <= 200% poverty | I3: =IFERROR(__xludf.DUMMYFUNCTION("IFERROR(SUM(FILTER(D:D, A:A=G3, C:C=H3, B:B=""18 to 64 years"")), 0) - IFERROR(SUM(FILTER(D:D, A:A=G3, C:C=H3, B:B=""40 to 64 years"")), 0)"),11061.0) -> 11061 | J3: =IFERROR(__xludf.DUMMYFUNCTION("IFERROR(SUM(FILTER(E:E, A:A=G3, C:C=H3, B:B=""18 to 64 years"")), 0) - IFERROR(SUM(FILTER(E:E, A:A=G3, C:C=H3, B:B=""40 to 64 years"")), 0)"),67751.0) -> 67751 | K3: =I3/J3 -> 0.16325958 | L3: 18-40
A4: Male | B4: 18 to 64 years | C4: <= 250% poverty | D4: 25345 | E4: 158812 | F4: 74403.06 | G4: Male | H4: <= 250% poverty | I4: =IFERROR(__xludf.DUMMYFUNCTION("IFERROR(SUM(FILTER(D:D, A:A=G4, C:C=H4, B:B=""18 to 64 years"")), 0) - IFERROR(SUM(FILTER(D:D, A:A=G4, C:C=H4, B:B=""40 to 64 years"")), 0)"),14703.0) -> 14703 | J4: =IFERROR(__xludf.DUMMYFUNCTION("IFERROR(SUM(FILTER(E:E, A:A=G4, C:C=H4, B:B=""18 to 64 years"")), 0) - IFERROR(SUM(FILTER(E:E, A:A=G4, C:C=H4, B:B=""40 to 64 years"")), 0)"),89991.0) -> 89991 | K4: =I4/J4 -> 0.163383 | L4: 18-40
A5: Male | B5: 18 to 64 years | C5: <= 400% of poverty | D5: 36383 | E5: 257797 | F5: 74403.06 | G5: Male | H5: <= 400% of poverty | I5: =IFERROR(__xludf.DUMMYFUNCTION("IFERROR(SUM(FILTER(D:D, A:A=G5, C:C=H5, B:B=""18 to 64 years"")), 0) - IFERROR(SUM(FILTER(D:D, A:A=G5, C:C=H5, B:B=""40 to 64 years"")), 0)"),21362.0) -> 21362 | J5: =IFERROR(__xludf.DUMMYFUNCTION("IFERROR(SUM(FILTER(E:E, A:A=G5, C:C=H5, B:B=""18 to 64 years"")), 0) - IFERROR(SUM(FILTER(E:E, A:A=G5, C:C=H5, B:B=""40 to 64 years"")), 0)"),146201.0) -> 146201 | K5: =I5/J5 -> 0.14611391 | L5: 18-40
A6: Male | B6: 18 to 64 years | C6: Between 138% and 400% of poverty | D6: 24785 | E6: 182764 | F6: 74403.06 | G6: Male | H6: Between 138% and 400% of poverty | I6: =IFERROR(__xludf.DUMMYFUNCTION("IFERROR(SUM(FILTER(D:D, A:A=G6, C:C=H6, B:B=""18 to 64 years"")), 0) - IFERROR(SUM(FILTER(D:D, A:A=G6, C:C=H6, B:B=""40 to 64 years"")), 0)"),14995.0) -> 14995 | J6: =IFERROR(__xludf.DUMMYFUNCTION("IFERROR(SUM(FILTER(E:E, A:A=G6, C:C=H6, B:B=""18 to 64 years"")), 0) - IFERROR(SUM(FILTER(E:E, A:A=G6, C:C=H6, B:B=""40 to 64 years"")), 0)"),104944.0) -> 104944 | K6: =I6/J6 -> 0.14288573 | L6: 18-40
A7: Female | B7: 18 to 64 years | C7: <= 138% of poverty | D7: 9233 | E7: 90030 | F7: 74403.06 | G7: Female | H7: <= 138% of poverty | I7: =IFERROR(__xludf.DUMMYFUNCTION("IFERROR(SUM(FILTER(D:D, A:A=G7, C:C=H7, B:B=""18 to 64 years"")), 0) - IFERROR(SUM(FILTER(D:D, A:A=G7, C:C=H7, B:B=""40 to 64 years"")), 0)"),5138.0) -> 5138 | J7: =IFERROR(__xludf.DUMMYFUNCTION("IFERROR(SUM(FILTER(E:E, A:A=G7, C:C=H7, B:B=""18 to 64 years"")), 0) - IFERROR(SUM(FILTER(E:E, A:A=G7, C:C=H7, B:B=""40 to 64 years"")), 0)"),50997.0) -> 50997 | K7: =I7/J7 -> 0.10075102 | L7: 18-40
A8: Female | B8: 18 to 64 years | C8: <= 200% poverty | D8: 13996 | E8: 137442 | F8: 74403.06 | G8: Female | H8: <= 200% poverty | I8: =IFERROR(__xludf.DUMMYFUNCTION("IFERROR(SUM(FILTER(D:D, A:A=G8, C:C=H8, B:B=""18 to 64 years"")), 0) - IFERROR(SUM(FILTER(D:D, A:A=G8, C:C=H8, B:B=""40 to 64 years"")), 0)"),7767.0) -> 7767 | J8: =IFERROR(__xludf.DUMMYFUNCTION("IFERROR(SUM(FILTER(E:E, A:A=G8, C:C=H8, B:B=""18 to 64 years"")), 0) - IFERROR(SUM(FILTER(E:E, A:A=G8, C:C=H8, B:B=""40 to 64 years"")), 0)"),77864.0) -> 77864 | K8: =I8/J8 -> 0.099750848 | L8: 18-40
A9: Female | B9: 18 to 64 years | C9: <= 250% poverty | D9: 17423 | E9: 175727 | F9: 74403.06 | G9: Female | H9: <= 250% poverty | I9: =IFERROR(__xludf.DUMMYFUNCTION("IFERROR(SUM(FILTER(D:D, A:A=G9, C:C=H9, B:B=""18 to 64 years"")), 0) - IFERROR(SUM(FILTER(D:D, A:A=G9, C:C=H9, B:B=""40 to 64 years"")), 0)"),9623.0) -> 9623 | J9: =IFERROR(__xludf.DUMMYFUNCTION("IFERROR(SUM(FILTER(E:E, A:A=G9, C:C=H9, B:B=""18 to 64 years"")), 0) - IFERROR(SUM(FILTER(E:E, A:A=G9, C:C=H9, B:B=""40 to 64 years"")), 0)"),99545.0) -> 99545 | K9: =I9/J9 -> 0.096669848 | L9: 18-40
A10: Female | B10: 18 to 64 years | C10: <= 400% of poverty | D10: 24617 | E10: 276963 | F10: 74403.06 | G10: Female | H10: <= 400% of poverty | I10: =IFERROR(__xludf.DUMMYFUNCTION("IFERROR(SUM(FILTER(D:D, A:A=G10, C:C=H10, B:B=""18 to 64 years"")), 0) - IFERROR(SUM(FILTER(D:D, A:A=G10, C:C=H10, B:B=""40 to 64 years"")), 0)"),13310.0) -> 13310 | J10: =IFERROR(__xludf.DUMMYFUNCTION("IFERROR(SUM(FILTER(E:E, A:A=G10, C:C=H10, B:B=""18 to 64 years"")), 0) - IFERROR(SUM(FILTER(E:E, A:A=G10, C:C=H10, B:B=""40 to 64 years"")), 0)"),153620.0) -> 153620 | K10: =I10/J10 -> 0.086642364 | L10: 18-40
A11: Female | B11: 18 to 64 years | C11: Between 138% and 400% of poverty | D11: 15384 | E11: 186933 | F11: 74403.06 | G11: Female | H11: Between 138% and 400% of poverty | I11: =IFERROR(__xludf.DUMMYFUNCTION("IFERROR(SUM(FILTER(D:D, A:A=G11, C:C=H11, B:B=""18 to 64 years"")), 0) - IFERROR(SUM(FILTER(D:D, A:A=G11, C:C=H11, B:B=""40 to 64 years"")), 0)"),8172.0) -> 8172 | J11: =IFERROR(__xludf.DUMMYFUNCTION("IFERROR(SUM(FILTER(E:E, A:A=G11, C:C=H11, B:B=""18 to 64 years"")), 0) - IFERROR(SUM(FILTER(E:E, A:A=G11, C:C=H11, B:B=""40 to 64 years"")), 0)"),102623.0) -> 102623 | K11: =I11/J11 -> 0.079631272 | L11: 18-40
A12: Male | B12: 40 to 64 years | C12: <= 138% of poverty | D12: 5231 | E12: 33776 | F12: 74403.06 | G12: Male | H12: <= 138% of poverty | I12: =IFERROR(__xludf.DUMMYFUNCTION("IFERROR(SUM(FILTER(D:D, A:A=G12, C:C=H12, B:B=""40 to 64 years"")), 0) - IFERROR(SUM(FILTER(D:D, A:A=G12, C:C=H12, B:B=""50 to 64 years"")), 0)"),3223.0) -> 3223 | J12: =IFERROR(__xludf.DUMMYFUNCTION("IFERROR(SUM(FILTER(E:E, A:A=G12, C:C=H12, B:B=""40 to 64 years"")), 0) - IFERROR(SUM(FILTER(E:E, A:A=G12, C:C=H12, B:B=""50 to 64 years"")), 0)"),13761.0) -> 13761 | K12: =I12/J12 -> 0.23421263 | L12: 40-50
A13: Male | B13: 40 to 64 years | C13: <= 200% poverty | D13: 8179 | E13: 52579 | F13: 74403.06 | G13: Male | H13: <= 200% poverty | I13: =IFERROR(__xludf.DUMMYFUNCTION("IFERROR(SUM(FILTER(D:D, A:A=G13, C:C=H13, B:B=""40 to 64 years"")), 0) - IFERROR(SUM(FILTER(D:D, A:A=G13, C:C=H13, B:B=""50 to 64 years"")), 0)"),5042.0) -> 5042 | J13: =IFERROR(__xludf.DUMMYFUNCTION("IFERROR(SUM(FILTER(E:E, A:A=G13, C:C=H13, B:B=""40 to 64 years"")), 0) - IFERROR(SUM(FILTER(E:E, A:A=G13, C:C=H13, B:B=""50 to 64 years"")), 0)"),22179.0) -> 22179 | K13: =I13/J13 -> 0.22733216 | L13: 40-50
A14: Male | B14: 40 to 64 years | C14: <= 250% poverty | D14: 10642 | E14: 68821 | F14: 74403.06 | G14: Male | H14: <= 250% poverty | I14: =IFERROR(__xludf.DUMMYFUNCTION("IFERROR(SUM(FILTER(D:D, A:A=G14, C:C=H14, B:B=""40 to 64 years"")), 0) - IFERROR(SUM(FILTER(D:D, A:A=G14, C:C=H14, B:B=""50 to 64 years"")), 0)"),6521.0) -> 6521 | J14: =IFERROR(__xludf.DUMMYFUNCTION("IFERROR(SUM(FILTER(E:E, A:A=G14, C:C=H14, B:B=""40 to 64 years"")), 0) - IFERROR(SUM(FILTER(E:E, A:A=G14, C:C=H14, B:B=""50 to 64 years"")), 0)"),29644.0) -> 29644 | K14: =I14/J14 -> 0.21997706 | L14: 40-50
A15: Male | B15: 40 to 64 years | C15: <= 400% of poverty | D15: 15021 | E15: 111596 | F15: 74403.06 | G15: Male | H15: <= 400% of poverty | I15: =IFERROR(__xludf.DUMMYFUNCTION("IFERROR(SUM(FILTER(D:D, A:A=G15, C:C=H15, B:B=""40 to 64 years"")), 0) - IFERROR(SUM(FILTER(D:D, A:A=G15, C:C=H15, B:B=""50 to 64 years"")), 0)"),8714.0) -> 8714 | J15: =IFERROR(__xludf.DUMMYFUNCTION("IFERROR(SUM(FILTER(E:E, A:A=G15, C:C=H15, B:B=""40 to 64 years"")), 0) - IFERROR(SUM(FILTER(E:E, A:A=G15, C:C=H15, B:B=""50 to 64 years"")), 0)"),48216.0) -> 48216 | K15: =I15/J15 -> 0.18072839 | L15: 40-50
A16: Male | B16: 40 to 64 years | C16: Between 138% and 400% of poverty | D16: 9790 | E16: 77820 | F16: 74403.06 | G16: Male | H16: Between 138% and 400% of poverty | I16: =IFERROR(__xludf.DUMMYFUNCTION("IFERROR(SUM(FILTER(D:D, A:A=G16, C:C=H16, B:B=""40 to 64 years"")), 0) - IFERROR(SUM(FILTER(D:D, A:A=G16, C:C=H16, B:B=""50 to 64 years"")), 0)"),5491.0) -> 5491 | J16: =IFERROR(__xludf.DUMMYFUNCTION("IFERROR(SUM(FILTER(E:E, A:A=G16, C:C=H16, B:B=""40 to 64 years"")), 0) - IFERROR(SUM(FILTER(E:E, A:A=G16, C:C=H16, B:B=""50 to 64 years"")), 0)"),34455.0) -> 34455 | K16: =I16/J16 -> 0.15936729 | L16: 40-50
A17: Female | B17: 40 to 64 years | C17: <= 138% of poverty | D17: 4095 | E17: 39033 | F17: 74403.06 | G17: Female | H17: <= 138% of poverty | I17: =IFERROR(__xludf.DUMMYFUNCTION("IFERROR(SUM(FILTER(D:D, A:A=G17, C:C=H17, B:B=""40 to 64 years"")), 0) - IFERROR(SUM(FILTER(D:D, A:A=G17, C:C=H17, B:B=""50 to 64 years"")), 0)"),1790.0) -> 1790 | J17: =IFERROR(__xludf.DUMMYFUNCTION("IFERROR(SUM(FILTER(E:E, A:A=G17, C:C=H17, B:B=""40 to 64 years"")), 0) - IFERROR(SUM(FILTER(E:E, A:A=G17, C:C=H17, B:B=""50 to 64 years"")), 0)"),15606.0) -> 15606 | K17: =I17/J17 -> 0.11469947 | L17: 40-50
A18: Female | B18: 40 to 64 years | C18: <= 200% poverty | D18: 6229 | E18: 59578 | F18: 74403.06 | G18: Female | H18: <= 200% poverty | I18: =IFERROR(__xludf.DUMMYFUNCTION("IFERROR(SUM(FILTER(D:D, A:A=G18, C:C=H18, B:B=""40 to 64 years"")), 0) - IFERROR(SUM(FILTER(D:D, A:A=G18, C:C=H18, B:B=""50 to 64 years"")), 0)"),2780.0) -> 2780 | J18: =IFERROR(__xludf.DUMMYFUNCTION("IFERROR(SUM(FILTER(E:E, A:A=G18, C:C=H18, B:B=""40 to 64 years"")), 0) - IFERROR(SUM(FILTER(E:E, A:A=G18, C:C=H18, B:B=""50 to 64 years"")), 0)"),24653.0) -> 24653 | K18: =I18/J18 -> 0.11276518 | L18: 40-50
A19: Female | B19: 40 to 64 years | C19: <= 250% poverty | D19: 7800 | E19: 76182 | F19: 74403.06 | G19: Female | H19: <= 250% poverty | I19: =IFERROR(__xludf.DUMMYFUNCTION("IFERROR(SUM(FILTER(D:D, A:A=G19, C:C=H19, B:B=""40 to 64 years"")), 0) - IFERROR(SUM(FILTER(D:D, A:A=G19, C:C=H19, B:B=""50 to 64 years"")), 0)"),3589.0) -> 3589 | J19: =IFERROR(__xludf.DUMMYFUNCTION("IFERROR(SUM(FILTER(E:E, A:A=G19, C:C=H19, B:B=""40 to 64 years"")), 0) - IFERROR(SUM(FILTER(E:E, A:A=G19, C:C=H19, B:B=""50 to 64 years"")), 0)"),32029.0) -> 32029 | K19: =I19/J19 -> 0.1120547 | L19: 40-50
A20: Female | B20: 40 to 64 years | C20: <= 400% of poverty | D20: 11307 | E20: 123343 | F20: 74403.06 | G20: Female | H20: <= 400% of poverty | I20: =IFERROR(__xludf.DUMMYFUNCTION("IFERROR(SUM(FILTER(D:D, A:A=G20, C:C=H20, B:B=""40 to 64 years"")), 0) - IFERROR(SUM(FILTER(D:D, A:A=G20, C:C=H20, B:B=""50 to 64 years"")), 0)"),5074.0) -> 5074 | J20: =IFERROR(__xludf.DUMMYFUNCTION("IFERROR(SUM(FILTER(E:E, A:A=G20, C:C=H20, B:B=""40 to 64 years"")), 0) - IFERROR(SUM(FILTER(E:E, A:A=G20, C:C=H20, B:B=""50 to 64 years"")), 0)"),51368.0) -> 51368 | K20: =I20/J20 -> 0.098777449 | L20: 40-50
A21: Female | B21: 40 to 64 years | C21: Between 138% and 400% of poverty | D21: 7212 | E21: 84310 | F21: 74403.06 | G21: Female | H21: Between 138% and 400% of poverty | I21: =IFERROR(__xludf.DUMMYFUNCTION("IFERROR(SUM(FILTER(D:D, A:A=G21, C:C=H21, B:B=""40 to 64 years"")), 0) - IFERROR(SUM(FILTER(D:D, A:A=G21, C:C=H21, B:B=""50 to 64 years"")), 0)"),3284.0) -> 3284 | J21: =IFERROR(__xludf.DUMMYFUNCTION("IFERROR(SUM(FILTER(E:E, A:A=G21, C:C=H21, B:B=""40 to 64 years"")), 0) - IFERROR(SUM(FILTER(E:E, A:A=G21, C:C=H21, B:B=""50 to 64 years"")), 0)"),35762.0) -> 35762 | K21: =I21/J21 -> 0.091829316 | L21: 40-50
A22: Male | B22: 50 to 64 years | C22: <= 138% of poverty | D22: 2008 | E22: 20015 | F22: 74403.06 | G22: Male | H22: <= 138% of poverty | I22: 2008 | J22: 20015 | K22: =I22/J22 -> 0.10032476 | L22: 50-64
A23: Male | B23: 50 to 64 years | C23: <= 200% poverty | D23: 3137 | E23: 30400 | F23: 74403.06 | G23: Male | H23: <= 200% poverty | I23: 3137 | J23: 30400 | K23: =I23/J23 -> 0.10319079 | L23: 50-64
A24: Male | B24: 50 to 64 years | C24: <= 250% poverty | D24: 4121 | E24: 39177 | F24: 74403.06 | G24: Male | H24: <= 250% poverty | I24: 4121 | J24: 39177 | K24: =I24/J24 -> 0.10518927 | L24: 50-64
A25: Male | B25: 50 to 64 years | C25: <= 400% of poverty | D25: 6307 | E25: 63380 | F25: 74403.06 | G25: Male | H25: <= 400% of poverty | I25: 6307 | J25: 63380 | K25: =I25/J25 -> 0.099510887 | L25: 50-64
A26: Male | B26: 50 to 64 years | C26: Between 138% and 400% of poverty | D26: 4299 | E26: 43365 | F26: 74403.06 | G26: Male | H26: Between 138% and 400% of poverty | I26: 4299 | J26: 43365 | K26: =I26/J26 -> 0.099135247 | L26: 50-64
A27: Female | B27: 50 to 64 years | C27: <= 138% of poverty | D27: 2305 | E27: 23427 | F27: 74403.06 | G27: Female | H27: <= 138% of poverty | I27: 2305 | J27: 23427 | K27: =I27/J27 -> 0.098390746 | L27: 50-64
A28: Female | B28: 50 to 64 years | C28: <= 200% poverty | D28: 3449 | E28: 34925 | F28: 74403.06 | G28: Female | H28: <= 200% poverty | I28: 3449 | J28: 34925 | K28: =I28/J28 -> 0.098754474 | L28: 50-64
A29: Female | B29: 50 to 64 years | C29: <= 250% poverty | D29: 4211 | E29: 44153 | F29: 74403.06 | G29: Female | H29: <= 250% poverty | I29: 4211 | J29: 44153 | K29: =I29/J29 -> 0.095372908 | L29: 50-64
A30: Female | B30: 50 to 64 years | C30: <= 400% of poverty | D30: 6233 | E30: 71975 | F30: 74403.06 | G30: Female | H30: <= 400% of poverty | I30: 6233 | J30: 71975 | K30: =I30/J30 -> 0.086599514 | L30: 50-64
A31: Female | B31: 50 to 64 years | C31: Between 138% and 400% of poverty | D31: 3928 | E31: 48548 | F31: 74403.06 | G31: Female | H31: Between 138% and 400% of poverty | I31: 3928 | J31: 48548 | K31: =I31/J31 -> 0.080909615 | L31: 50-64
A34: SOURCES: | B34: expected stays | D34: https://datatools.ahrq.gov/hcup-fast-stats/
B35: expected cost | D35: https://datatools.ahrq.gov/hcup-fast-stats/
A36: Model- Based SAHIE Estimates for Counties and States: 2020 | B36: insured/uninsured by demographic | D36: https://www.census.gov/data/datasets/time-series/demo/sahie/estimates-acs.html
A37: 2020 CY Hospital Annual Selected File (October 2022 Extract)XLSX | B37: expected cost per uninsured stay | D37: https://data.chhs.ca.gov/dataset/hospital-annual-financial-data-selected-data-pivot-tables
A38: 2020 CY Hospital Annual Selected File (October 2022 Extract)XLSX | B38: # of uninsured stays | D38: https://data.chhs.ca.gov/dataset/hospital-annual-financial-data-selected-data-pivot-tables
B39: age freq: | D39: https://www.cdc.gov/nchs/hus/topics/hospitalization.htm#explore-data | People with hospital stays in the past year, by selected characteristics: United States, selected years 1997–2019

Sheet Analysis
A1: uninsured_pop | B1: insured-pop | C1: % uninsured | D1: income range | E1: total demographic expected cost for uninsurance | F1: expected unisured cost per person | G1: expected price to insure | H1: expected difference | I1: expected stays | J1: total mult | K1: frequency mult | L1: severity mult | M1: expected by age | N1: age mult | O1: expected by sex | P1: sex mult | Q1: expected by income | R1: Income Severity Mult | S1: % of pop w/ Hospitalizations by age | U1: Rate of Inpatient Stays by Sex | W1: Rate of Inpatient Stays by Community Income | Y1: Insurance Age Mult
A2: ='Raw Data'!I2 -> 6367 | B2: ='Raw Data'!J2 -> 41257 | C2: =A2/B2 -> 0.15432533 | D2: <=138% | E2: =A2*F2 -> 32695061 | F2: =freq*exp*J2 -> 5135.081 | G2: =ins*Y2 -> 4921.7403 | H2: =F2-G2 -> 213.34064 | I2: =A2*freq*K2 -> 529.99985 | J2: =K2*L2 -> 0.81716636 | K2: =T2*V2*X2 -> 0.98558681 | L2: =N2*P2 -> 0.82911658 | M2: 9049.7 | N2: =2*M2/(M2+M12) -> 0.73516223 | O2: 14412.9 | P2: =O2/(14412.9+11146.4)*2 -> 1.1278008 | Q2: 11725.8 | R2: =Q2*4/(11725.8+12147.5+12897+14103) -> 0.92196103 | S2: 6.6 | T2: =S2*(young+mid+old)/(6.6*young+7.2*mid+10.1*old) -> 0.88529669 | U2: 8915.6 | V2: =U2*2/(8915.6+10644.6) -> 0.91160622 | W2: 11753 | X2: =W2*4/(11753+10124.9+8995.5+7622.1) -> 1.2212337 | Y2: 1.087
A3: ='Raw Data'!I3-'Raw Data'!I2 -> 4694 | B3: ='Raw Data'!J3-'Raw Data'!J2 -> 26494 | C3: =A3/B3 -> 0.17717219 | D3: 138%-200% | E3: =A3*F3 -> 20765022 | F3: =freq*exp*J3 -> 4423.737 | G3: =ins*Y3 -> 4921.7403 | H3: =F3-G3 -> -498.0033 | I3: =A3*freq*K3 -> 336.60921 | J3: =K3*L3 -> 0.7039673 | K3: =T3*V3*X3 -> 0.84905708 | L3: =N3*P3 -> 0.82911658 | M3: 9049.7 | N3: =2*M3/(M3+M13) -> 0.73516223 | O3: 14412.9 | P3: =O3/(14412.9+11146.4)*2 -> 1.1278008 | Q3: 12147.5 | R3: =Q3*4/(11725.8+12147.5+12897+14103) -> 0.95511791 | S3: 6.6 | T3: =S3*(young+mid+old)/(6.6*young+7.2*mid+10.1*old) -> 0.88529669 | U3: 8915.6 | V3: =U3*2/(8915.6+10644.6) -> 0.91160622 | W3: 10124.9 | X3: =W3*4/(11753+10124.9+8995.5+7622.1) -> 1.0520606 | Y3: 1.087
A4: ='Raw Data'!I4-'Raw Data'!I3 -> 3642 | B4: ='Raw Data'!J4-'Raw Data'!J3 -> 22240 | C4: =A4/B4 -> 0.16375899 | D4: 200%-250% | E4: =A4*F4 -> 14314092 | F4: =freq*exp*J4 -> 3930.2834 | G4: =ins*Y4 -> 4921.7403 | H4: =F4-G4 -> -991.45692 | I4: =A4*freq*K4 -> 232.03709 | J4: =K4*L4 -> 0.62544202 | K4: =T4*V4*X4 -> 0.7543475 | L4: =N4*P4 -> 0.82911658 | M4: 9049.7 | N4: =2*M4/(M4+M14) -> 0.73516223 | O4: 14412.9 | P4: =O4/(14412.9+11146.4)*2 -> 1.1278008 | Q4: 12897 | R4: =Q4*4/(11725.8+12147.5+12897+14103) -> 1.0140486 | S4: 6.6 | T4: =S4*(young+mid+old)/(6.6*young+7.2*mid+10.1*old) -> 0.88529669 | U4: 8915.6 | V4: =U4*2/(8915.6+10644.6) -> 0.91160622 | W4: 8995.5 | X4: =W4*4/(11753+10124.9+8995.5+7622.1) -> 0.93470665 | Y4: 1.087
A5: ='Raw Data'!I5-'Raw Data'!I4 -> 6659 | B5: ='Raw Data'!J5-'Raw Data'!J4 -> 56210 | C5: =A5/B5 -> 0.11846647 | D5: 250%-400% | E5: =A5*F5 -> 22175949 | F5: =freq*exp*J5 -> 3330.2221 | G5: =ins*Y5 -> 4921.7403 | H5: =F5-G5 -> -1591.5182 | I5: =A5*freq*K5 -> 359.4809 | J5: =K5*L5 -> 0.52995182 | K5: =T5*V5*X5 -> 0.63917648 | L5: =N5*P5 -> 0.82911658 | M5: 9049.7 | N5: =2*M5/(M5+M15) -> 0.73516223 | O5: 14412.9 | P5: =O5/(14412.9+11146.4)*2 -> 1.1278008 | Q5: 14103 | R5: =Q5*4/(11725.8+12147.5+12897+14103) -> 1.1088724 | S5: 6.6 | T5: =S5*(young+mid+old)/(6.6*young+7.2*mid+10.1*old) -> 0.88529669 | U5: 8915.6 | V5: =U5*2/(8915.6+10644.6) -> 0.91160622 | W5: 7622.1 | X5: =W5*4/(11753+10124.9+8995.5+7622.1) -> 0.79199906 | Y5: 1.087
Y6: 1.087
A7: ='Raw Data'!I7 -> 5138 | B7: ='Raw Data'!J7 -> 50997 | C7: =A7/B7 -> 0.10075102 | D7: <=138% | E7: =A7*F7 -> 24361466 | F7: =freq*exp*J7 -> 4741.4297 | G7: =ins*Y7 -> 4921.7403 | H7: =F7-G7 -> -180.31061 | I7: =A7*freq*K7 -> 510.63875 | J7: =K7*L7 -> 0.75452303 | K7: =T7*V7*X7 -> 1.1767214 | L7: =N7*P7 -> 0.64120788 | M7: 9049.7 | N7: =2*M7/(M7+M17) -> 0.73516223 | O7: 11146.4 | P7: =O7/(14412.9+11146.4)*2 -> 0.87219916 | Q7: 11725.8 | R7: =Q7*4/(11725.8+12147.5+12897+14103) -> 0.92196103 | S7: 6.6 | T7: =S7*(young+mid+old)/(6.6*young+7.2*mid+10.1*old) -> 0.88529669 | U7: 10644.6 | V7: =U7*2/(8915.6+10644.6) -> 1.0883938 | W7: 11753 | X7: =W7*4/(11753+10124.9+8995.5+7622.1) -> 1.2212337 | Y7: 1.087
A8: ='Raw Data'!I8-'Raw Data'!I7 -> 2629 | B8: ='Raw Data'!J8-'Raw Data'!J7 -> 26867 | C8: =A8/B8 -> 0.097852384 | D8: 138%-200% | E8: =A8*F8 -> 10738458 | F8: =freq*exp*J8 -> 4084.6169 | G8: =ins*Y8 -> 4921.7403 | H8: =F8-G8 -> -837.12349 | I8: =A8*freq*K8 -> 225.08796 | J8: =K8*L8 -> 0.65000172 | K8: =T8*V8*X8 -> 1.0137145 | L8: =N8*P8 -> 0.64120788 | M8: 9049.7 | N8: =2*M8/(M8+M18) -> 0.73516223 | O8: 11146.4 | P8: =O8/(14412.9+11146.4)*2 -> 0.87219916 | Q8: 12147.5 | R8: =Q8*4/(11725.8+12147.5+12897+14103) -> 0.95511791 | S8: 6.6 | T8: =S8*(young+mid+old)/(6.6*young+7.2*mid+10.1*old) -> 0.88529669 | U8: 10644.6 | V8: =U8*2/(8915.6+10644.6) -> 1.0883938 | W8: 10124.9 | X8: =W8*4/(11753+10124.9+8995.5+7622.1) -> 1.0520606 | Y8: 1.087
A9: ='Raw Data'!I9-'Raw Data'!I8 -> 1856 | B9: ='Raw Data'!J9-'Raw Data'!J8 -> 21681 | C9: =A9/B9 -> 0.085604908 | D9: 200%-250% | E9: =A9*F9 -> 6735407.3 | F9: =freq*exp*J9 -> 3628.991 | G9: =ins*Y9 -> 4921.7403 | H9: =F9-G9 -> -1292.7493 | I9: =A9*freq*K9 -> 141.18034 | J9: =K9*L9 -> 0.57749612 | K9: =T9*V9*X9 -> 0.90063791 | L9: =N9*P9 -> 0.64120788 | M9: 9049.7 | N9: =2*M9/(M9+M19) -> 0.73516223 | O9: 11146.4 | P9: =O9/(14412.9+11146.4)*2 -> 0.87219916 | Q9: 12897 | R9: =Q9*4/(11725.8+12147.5+12897+14103) -> 1.0140486 | S9: 6.6 | T9: =S9*(young+mid+old)/(6.6*young+7.2*mid+10.1*old) -> 0.88529669 | U9: 10644.6 | V9: =U9*2/(8915.6+10644.6) -> 1.0883938 | W9: 8995.5 | X9: =W9*4/(11753+10124.9+8995.5+7622.1) -> 0.93470665 | Y9: 1.087
A10: ='Raw Data'!I10-'Raw Data'!I9 -> 3687 | B10: ='Raw Data'!J10-'Raw Data'!J9 -> 54075 | C10: =A10/B10 -> 0.068183079 | D10: 250%-400% | E10: =A10*F10 -> 11337267 | F10: =freq*exp*J10 -> 3074.9299 | G10: =ins*Y10 -> 4921.7403 | H10: =F10-G10 -> -1846.8104 | I10: =A10*freq*K10 -> 237.63955 | J10: =K10*L10 -> 0.48932613 | K10: =T10*V10*X10 -> 0.76313181 | L10: =N10*P10 -> 0.64120788 | M10: 9049.7 | N10: =2*M10/(M10+M20) -> 0.73516223 | O10: 11146.4 | P10: =O10/(14412.9+11146.4)*2 -> 0.87219916 | Q10: 14103 | R10: =Q10*4/(11725.8+12147.5+12897+14103) -> 1.1088724 | S10: 6.6 | T10: =S10*(young+mid+old)/(6.6*young+7.2*mid+10.1*old) -> 0.88529669 | U10: 10644.6 | V10: =U10*2/(8915.6+10644.6) -> 1.0883938 | W10: 7622.1 | X10: =W10*4/(11753+10124.9+8995.5+7622.1) -> 0.79199906 | Y10: 1.087
A11: =SUM(A2:A10) -> 34672
A12: ='Raw Data'!I12 -> 3223 | B12: ='Raw Data'!J12 -> 13761 | C12: =A12/B12 -> 0.23421263 | D12: <=138% | E12: =A12*F12 -> 31063315 | F12: =freq*exp*J12 -> 9638.0128 | G12: =ins*Y12 -> 6538.1721 | H12: =F12-G12 -> 3099.8407 | I12: =A12*freq*K12 -> 292.67779 | J12: =K12*L12 -> 1.5337363 | K12: =T12*V12*X12 -> 1.0751856 | L12: =N12*P12 -> 1.4264851 | M12: 15569.9 | N12: =2*M12/(M12+M4) -> 1.2648378 | O12: 14412.9 | P12: =O12/(14412.9+11146.4)*2 -> 1.1278008 | Q12: 11725.8 | R12: =Q12*4/(11725.8+12147.5+12897+14103) -> 0.92196103 | S12: 7.2 | T12: =S12*(young+mid+old)/(6.6*young+7.2*mid+10.1*old) -> 0.9657782 | U12: 8915.6 | V12: =U12*2/(8915.6+10644.6) -> 0.91160622 | W12: 11753 | X12: =W12*4/(11753+10124.9+8995.5+7622.1) -> 1.2212337 | Y12: 1.444
A13: ='Raw Data'!I13-'Raw Data'!I12 -> 1819 | B13: ='Raw Data'!J13-'Raw Data'!J12 -> 8418 | C13: =A13/B13 -> 0.21608458 | D13: 138%-200% | E13: =A13*F13 -> 15102965 | F13: =freq*exp*J13 -> 8302.8942 | G13: =ins*Y13 -> 6538.1721 | H13: =F13-G13 -> 1764.7221 | I13: =A13*freq*K13 -> 142.29976 | J13: =K13*L13 -> 1.3212734 | K13: =T13*V13*X13 -> 0.92624409 | L13: =N13*P13 -> 1.4264851 | M13: 15569.9 | N13: =2*M13/(M13+M5) -> 1.2648378 | O13: 14412.9 | P13: =O13/(14412.9+11146.4)*2 -> 1.1278008 | Q13: 12147.5 | R13: =Q13*4/(11725.8+12147.5+12897+14103) -> 0.95511791 | S13: 7.2 | T13: =S13*(young+mid+old)/(6.6*young+7.2*mid+10.1*old) -> 0.9657782 | U13: 8915.6 | V13: =U13*2/(8915.6+10644.6) -> 0.91160622 | W13: 10124.9 | X13: =W13*4/(11753+10124.9+8995.5+7622.1) -> 1.0520606 | Y13: 1.444
A14: ='Raw Data'!I14-'Raw Data'!I13 -> 1479 | B14: ='Raw Data'!J14-'Raw Data'!J13 -> 7465 | C14: =A14/B14 -> 0.19812458 | D14: 200%-250% | E14: =A14*F14 -> 10910188 | F14: =freq*exp*J14 -> 7376.7331 | G14: =ins*Y14 -> 6538.1721 | H14: =F14-G14 -> 838.56102 | I14: =A14*freq*K14 -> 102.79552 | J14: =K14*L14 -> 1.1738896 | K14: =T14*V14*X14 -> 0.82292454 | L14: =N14*P14 -> 1.4264851 | M14: 15569.9 | N14: =2*M13/(M13+M5) -> 1.2648378 | O14: 14412.9 | P14: =O14/(14412.9+11146.4)*2 -> 1.1278008 | Q14: 12897 | R14: =Q14*4/(11725.8+12147.5+12897+14103) -> 1.0140486 | S14: 7.2 | T14: =S14*(young+mid+old)/(6.6*young+7.2*mid+10.1*old) -> 0.9657782 | U14: 8915.6 | V14: =U14*2/(8915.6+10644.6) -> 0.91160622 | W14: 8995.5 | X14: =W14*4/(11753+10124.9+8995.5+7622.1) -> 0.93470665 | Y14: 1.444
A15: ='Raw Data'!I15-'Raw Data'!I14 -> 2193 | B15: ='Raw Data'!J15-'Raw Data'!J14 -> 18572 | C15: =A15/B15 -> 0.11808098 | D15: 250%-400% | E15: =A15*F15 -> 13707304 | F15: =freq*exp*J15 -> 6250.4805 | G15: =ins*Y15 -> 6538.1721 | H15: =F15-G15 -> -287.69157 | I15: =A15*freq*K15 -> 129.14988 | J15: =K15*L15 -> 0.99466443 | K15: =T15*V15*X15 -> 0.69728344 | L15: =N15*P15 -> 1.4264851 | M15: 15569.9 | N15: =2*M15/(M15+M7) -> 1.2648378 | O15: 14412.9 | P15: =O15/(14412.9+11146.4)*2 -> 1.1278008 | Q15: 14103 | R15: =Q15*4/(11725.8+12147.5+12897+14103) -> 1.1088724 | S15: 7.2 | T15: =S15*(young+mid+old)/(6.6*young+7.2*mid+10.1*old) -> 0.9657782 | U15: 8915.6 | V15: =U15*2/(8915.6+10644.6) -> 0.91160622 | W15: 7622.1 | X15: =W15*4/(11753+10124.9+8995.5+7622.1) -> 0.79199906 | Y15: 1.444
A17: ='Raw Data'!I17 -> 1790 | B17: ='Raw Data'!J17 -> 15606 | C17: =A17/B17 -> 0.11469947 | D17: <=138% | E17: =A17*F17 -> 15929515 | F17: =freq*exp*J17 -> 8899.1704 | G17: =ins*Y17 -> 6538.1721 | H17: =F17-G17 -> 2360.9983 | I17: =A17*freq*K17 -> 194.07128 | J17: =K17*L17 -> 1.4161612 | K17: =T17*V17*X17 -> 1.2836961 | L17: =N17*P17 -> 1.1031904 | M17: 15569.9 | N17: =2*M13/(M13+M5) -> 1.2648378 | O17: 11146.4 | P17: =O17/(14412.9+11146.4)*2 -> 0.87219916 | Q17: 11725.8 | R17: =Q17*4/(11725.8+12147.5+12897+14103) -> 0.92196103 | S17: 7.2 | T17: =S17*(young+mid+old)/(6.6*young+7.2*mid+10.1*old) -> 0.9657782 | U17: 10644.6 | V17: =U17*2/(8915.6+10644.6) -> 1.0883938 | W17: 11753 | X17: =W17*4/(11753+10124.9+8995.5+7622.1) -> 1.2212337 | Y17: 1.444
A18: ='Raw Data'!I18-'Raw Data'!I17 -> 990 | B18: ='Raw Data'!J18-'Raw Data'!J17 -> 9047 | C18: =A18/B18 -> 0.10942854 | D18: 138%-200% | E18: =A18*F18 -> 7589736.9 | F18: =freq*exp*J18 -> 7666.4009 | G18: =ins*Y18 -> 6538.1721 | H18: =F18-G18 -> 1128.2288 | I18: =A18*freq*K18 -> 92.466716 | J18: =K18*L18 -> 1.2199856 | K18: =T18*V18*X18 -> 1.1058704 | L18: =N18*P18 -> 1.1031904 | M18: 15569.9 | N18: =2*M13/(M13+M5) -> 1.2648378 | O18: 11146.4 | P18: =O18/(14412.9+11146.4)*2 -> 0.87219916 | Q18: 12147.5 | R18: =Q18*4/(11725.8+12147.5+12897+14103) -> 0.95511791 | S18: 7.2 | T18: =S18*(young+mid+old)/(6.6*young+7.2*mid+10.1*old) -> 0.9657782 | U18: 10644.6 | V18: =U18*2/(8915.6+10644.6) -> 1.0883938 | W18: 10124.9 | X18: =W18*4/(11753+10124.9+8995.5+7622.1) -> 1.0520606 | Y18: 1.444
A19: ='Raw Data'!I19-'Raw Data'!I18 -> 809 | B19: ='Raw Data'!J19-'Raw Data'!J18 -> 7376 | C19: =A19/B19 -> 0.10968004 | D19: 200%-250% | E19: =A19*F19 -> 5510292 | F19: =freq*exp*J19 -> 6811.2386 | G19: =ins*Y19 -> 6538.1721 | H19: =F19-G19 -> 273.06649 | I19: =A19*freq*K19 -> 67.132578 | J19: =K19*L19 -> 1.0839001 | K19: =T19*V19*X19 -> 0.98251408 | L19: =N19*P19 -> 1.1031904 | M19: 15569.9 | N19: =2*M13/(M13+M5) -> 1.2648378 | O19: 11146.4 | P19: =O19/(14412.9+11146.4)*2 -> 0.87219916 | Q19: 12897 | R19: =Q19*4/(11725.8+12147.5+12897+14103) -> 1.0140486 | S19: 7.2 | T19: =S19*(young+mid+old)/(6.6*young+7.2*mid+10.1*old) -> 0.9657782 | U19: 10644.6 | V19: =U19*2/(8915.6+10644.6) -> 1.0883938 | W19: 8995.5 | X19: =W19*4/(11753+10124.9+8995.5+7622.1) -> 0.93470665 | Y19: 1.444
A20: ='Raw Data'!I20-'Raw Data'!I19 -> 1485 | B20: ='Raw Data'!J20-'Raw Data'!J19 -> 19339 | C20: =A20/B20 -> 0.076787838 | D20: 250%-400% | E20: =A20*F20 -> 8570415.6 | F20: =freq*exp*J20 -> 5771.3236 | G20: =ins*Y20 -> 6538.1721 | H20: =F20-G20 -> -766.84847 | I20: =A20*freq*K20 -> 104.41445 | J20: =K20*L20 -> 0.91841424 | K20: =T20*V20*X20 -> 0.83250743 | L20: =N20*P20 -> 1.1031904 | M20: 15569.9 | N20: =2*M13/(M13+M5) -> 1.2648378 | O20: 11146.4 | P20: =O20/(14412.9+11146.4)*2 -> 0.87219916 | Q20: 14103 | R20: =Q20*4/(11725.8+12147.5+12897+14103) -> 1.1088724 | S20: 7.2 | T20: =S20*(young+mid+old)/(6.6*young+7.2*mid+10.1*old) -> 0.9657782 | U20: 10644.6 | V20: =U20*2/(8915.6+10644.6) -> 1.0883938 | W20: 7622.1 | X20: =W20*4/(11753+10124.9+8995.5+7622.1) -> 0.79199906 | Y20: 1.444
A21: =SUM(A12:A20) -> 13788
A22: ='Raw Data'!I22 -> 2008 | B22: ='Raw Data'!J22 -> 20015 | C22: =A22/B22 -> 0.10032476 | D22: <=138% | E22: =A22*F22 -> 27148140 | F22: =freq*exp*J22 -> 13519.99 | G22: =ins*Y22 -> 11034.297 | H22: =F22-G22 -> 2485.6928 | I22: =A22*freq*K22 -> 255.78911 | J22: =K22*L22 -> 2.1514911 | K22: =T22*V22*X22 -> 1.5082465 | L22: =N22*P22 -> 1.4264851 | M22: 15569.9 | N22: =2*M13/(M13+M5) -> 1.2648378 | O22: 14412.9 | P22: =O22/(14412.9+11146.4)*2 -> 1.1278008 | Q22: 11725.8 | R22: =Q22*4/(11725.8+12147.5+12897+14103) -> 0.92196103 | S22: 10.1 | T22: =S22*(young+mid+old)/(6.6*young+7.2*mid+10.1*old) -> 1.3547722 | U22: 8915.6 | V22: =U22*2/(8915.6+10644.6) -> 0.91160622 | W22: 11753 | X22: =W22*4/(11753+10124.9+8995.5+7622.1) -> 1.2212337 | Y22: 2.437
A23: ='Raw Data'!I23-'Raw Data'!I22 -> 1129 | B23: ='Raw Data'!J23-'Raw Data'!J22 -> 10385 | C23: =A23/B23 -> 0.10871449 | D23: 138%-200% | E23: =A23*F23 -> 13149593 | F23: =freq*exp*J23 -> 11647.116 | G23: =ins*Y23 -> 11034.297 | H23: =F23-G23 -> 612.81817 | I23: =A23*freq*K23 -> 123.89514 | J23: =K23*L23 -> 1.853453 | K23: =T23*V23*X23 -> 1.2993146 | L23: =N23*P23 -> 1.4264851 | M23: 15569.9 | N23: =2*M13/(M13+M5) -> 1.2648378 | O23: 14412.9 | P23: =O23/(14412.9+11146.4)*2 -> 1.1278008 | Q23: 12147.5 | R23: =Q23*4/(11725.8+12147.5+12897+14103) -> 0.95511791 | S23: 10.1 | T23: =S23*(young+mid+old)/(6.6*young+7.2*mid+10.1*old) -> 1.3547722 | U23: 8915.6 | V23: =U23*2/(8915.6+10644.6) -> 0.91160622 | W23: 10124.9 | X23: =W23*4/(11753+10124.9+8995.5+7622.1) -> 1.0520606 | Y23: 2.437
A24: ='Raw Data'!I24-'Raw Data'!I23 -> 984 | B24: ='Raw Data'!J24-'Raw Data'!J23 -> 8777 | C24: =A24/B24 -> 0.1121112 | D24: 200%-250% | E24: =A24*F24 -> 10182351 | F24: =freq*exp*J24 -> 10347.917 | G24: =ins*Y24 -> 11034.297 | H24: =F24-G24 -> -686.38007 | I24: =A24*freq*K24 -> 95.937856 | J24: =K24*L24 -> 1.6467062 | K24: =T24*V24*X24 -> 1.1543803 | L24: =N24*P24 -> 1.4264851 | M24: 15569.9 | N24: =2*M13/(M13+M5) -> 1.2648378 | O24: 14412.9 | P24: =O24/(14412.9+11146.4)*2 -> 1.1278008 | Q24: 12897 | R24: =Q24*4/(11725.8+12147.5+12897+14103) -> 1.0140486 | S24: 10.1 | T24: =S24*(young+mid+old)/(6.6*young+7.2*mid+10.1*old) -> 1.3547722 | U24: 8915.6 | V24: =U24*2/(8915.6+10644.6) -> 0.91160622 | W24: 8995.5 | X24: =W24*4/(11753+10124.9+8995.5+7622.1) -> 0.93470665 | Y24: 2.437
A25: ='Raw Data'!I25-'Raw Data'!I24 -> 2186 | B25: ='Raw Data'!J25-'Raw Data'!J24 -> 24203 | C25: =A25/B25 -> 0.090319382 | D25: 250%-400% | E25: =A25*F25 -> 19166925 | F25: =freq*exp*J25 -> 8768.0352 | G25: =ins*Y25 -> 11034.297 | H25: =F25-G25 -> -2266.2622 | I25: =A25*freq*K25 -> 180.59029 | J25: =K25*L25 -> 1.3952932 | K25: =T25*V25*X25 -> 0.97813371 | L25: =N25*P25 -> 1.4264851 | M25: 15569.9 | N25: =2*M13/(M13+M5) -> 1.2648378 | O25: 14412.9 | P25: =O25/(14412.9+11146.4)*2 -> 1.1278008 | Q25: 14103 | R25: =Q25*4/(11725.8+12147.5+12897+14103) -> 1.1088724 | S25: 10.1 | T25: =S25*(young+mid+old)/(6.6*young+7.2*mid+10.1*old) -> 1.3547722 | U25: 8915.6 | V25: =U25*2/(8915.6+10644.6) -> 0.91160622 | W25: 7622.1 | X25: =W25*4/(11753+10124.9+8995.5+7622.1) -> 0.79199906 | Y25: 2.437
A27: ='Raw Data'!I27 -> 2305 | B27: ='Raw Data'!J27 -> 23427 | C27: =A27/B27 -> 0.098390746 | D27: <=138% | E27: =A27*F27 -> 28774602 | F27: =freq*exp*J27 -> 12483.558 | G27: =ins*Y27 -> 11034.297 | H27: =F27-G27 -> 1449.2611 | I27: =A27*freq*K27 -> 350.56458 | J27: =K27*L27 -> 1.9865595 | K27: =T27*V27*X27 -> 1.8007403 | L27: =N27*P27 -> 1.1031904 | M27: 15569.9 | N27: =2*M13/(M13+M5) -> 1.2648378 | O27: 11146.4 | P27: =O27/(14412.9+11146.4)*2 -> 0.87219916 | Q27: 11725.8 | R27: =Q27*4/(11725.8+12147.5+12897+14103) -> 0.92196103 | S27: 10.1 | T27: =S27*(young+mid+old)/(6.6*young+7.2*mid+10.1*old) -> 1.3547722 | U27: 10644.6 | V27: =U27*2/(8915.6+10644.6) -> 1.0883938 | W27: 11753 | X27: =W27*4/(11753+10124.9+8995.5+7622.1) -> 1.2212337 | Y27: 2.437
A28: ='Raw Data'!I28-'Raw Data'!I27 -> 1144 | B28: ='Raw Data'!J28-'Raw Data'!J27 -> 11498 | C28: =A28/B28 -> 0.099495564 | D28: 138%-200% | E28: =A28*F28 -> 12302870 | F28: =freq*exp*J28 -> 10754.257 | G28: =ins*Y28 -> 11034.297 | H28: =F28-G28 -> -280.04051 | I28: =A28*freq*K28 -> 149.88741 | J28: =K28*L28 -> 1.7113687 | K28: =T28*V28*X28 -> 1.5512904 | L28: =N28*P28 -> 1.1031904 | M28: 15569.9 | N28: =2*M13/(M13+M5) -> 1.2648378 | O28: 11146.4 | P28: =O28/(14412.9+11146.4)*2 -> 0.87219916 | Q28: 12147.5 | R28: =Q28*4/(11725.8+12147.5+12897+14103) -> 0.95511791 | S28: 10.1 | T28: =S28*(young+mid+old)/(6.6*young+7.2*mid+10.1*old) -> 1.3547722 | U28: 10644.6 | V28: =U28*2/(8915.6+10644.6) -> 1.0883938 | W28: 10124.9 | X28: =W28*4/(11753+10124.9+8995.5+7622.1) -> 1.0520606 | Y28: 2.437
A29: ='Raw Data'!I29-'Raw Data'!I28 -> 762 | B29: ='Raw Data'!J29-'Raw Data'!J28 -> 9228 | C29: =A29/B29 -> 0.082574772 | D29: 200%-250% | E29: =A29*F29 -> 7280646.4 | F29: =freq*exp*J29 -> 9554.6541 | G29: =ins*Y29 -> 11034.297 | H29: =F29-G29 -> -1479.6432 | I29: =A29*freq*K29 -> 88.701028 | J29: =K29*L29 -> 1.520471 | K29: =T29*V29*X29 -> 1.3782489 | L29: =N29*P29 -> 1.1031904 | M29: 15569.9 | N29: =2*M13/(M13+M5) -> 1.2648378 | O29: 11146.4 | P29: =O29/(14412.9+11146.4)*2 -> 0.87219916 | Q29: 12897 | R29: =Q29*4/(11725.8+12147.5+12897+14103) -> 1.0140486 | S29: 10.1 | T29: =S29*(young+mid+old)/(6.6*young+7.2*mid+10.1*old) -> 1.3547722 | U29: 10644.6 | V29: =U29*2/(8915.6+10644.6) -> 1.0883938 | W29: 8995.5 | X29: =W29*4/(11753+10124.9+8995.5+7622.1) -> 0.93470665 | Y29: 2.437
A30: ='Raw Data'!I30-'Raw Data'!I29 -> 2022 | B30: ='Raw Data'!J30-'Raw Data'!J29 -> 27822 | C30: =A30/B30 -> 0.072676299 | D30: 250%-400% | E30: =A30*F30 -> 16369878 | F30: =freq*exp*J30 -> 8095.8845 | G30: =ins*Y30 -> 11034.297 | H30: =F30-G30 -> -2938.4128 | I30: =A30*freq*K30 -> 199.43628 | J30: =K30*L30 -> 1.2883311 | K30: =T30*V30*X30 -> 1.1678229 | L30: =N30*P30 -> 1.1031904 | M30: 15569.9 | N30: =2*M13/(M13+M5) -> 1.2648378 | O30: 11146.4 | P30: =O30/(14412.9+11146.4)*2 -> 0.87219916 | Q30: 14103 | R30: =Q30*4/(11725.8+12147.5+12897+14103) -> 1.1088724 | S30: 10.1 | T30: =S30*(young+mid+old)/(6.6*young+7.2*mid+10.1*old) -> 1.3547722 | U30: 10644.6 | V30: =U30*2/(8915.6+10644.6) -> 1.0883938 | W30: 7622.1 | X30: =W30*4/(11753+10124.9+8995.5+7622.1) -> 0.79199906 | Y30: 2.437
A31: =SUM(A22:A30) -> 12540 | D31: expected cost | E31: =sum(E2:E30) -> 3.8588146e+08 | F31: expected discharges | I31: =sum(I2:I30) -> 5142.4833
A32: total uninsured | B32: total uninsured discharges | C32: frequency | D32: actual cost | E32: 383324565 | F32: actual discharges | I32: 5152
A33: =sum(A2:A30) -> 109460 | B33: 5152 (hadr) | C33: =5152/61000 -> 0.084459016 | D33: difference: | E33: =(abs(E31-E32))/E31 -> 0.0066261114 | I33: =abs(I31-I32)/I32 -> 0.0018471807
B35: insurance base price | C35: 4527.82

Sheet EXPECTED COST TO INSURE
A1: EXPECTED COST TO INSURE
A2: https://hbex.coveredca.com/data-research/
A3: 2020 Covered California Data
A4: "2020 Individual Product Prices for all Health Insurance Companies"
A5: Second Highest For a 21 y/o Silver: | B5: 70285CA8060003 | C5: Rating Area 3 | D5: 21 | E5: 377.318 | F5: Blue Shield | G5: 70285 | H5: Silver | I5: HMO | J5: Copay | K5: Silver 70 Trio HMO
A6: Annual: | B6: =E5*12 -> 4527.816
A8: multiplier: | B8: 21 | C8: 1
A9: https://www.cms.gov/CCIIO/Programs-and-Initiatives/Health-Insurance-Market-Reforms/Downloads/StateSpecAgeCrv053117.pdf | B9: 28 | C9: 1.087
B10: 45 | C10: 1.444
B11: 57 | C11: 2.437
B12: 52 | C12: 1.952
C13: 4527.82

Sheet Open Solver
A1: Demographic | B1: Uninsured Population | C1: Expected Cost Per Uninsured | D1: Expected Cost to Insure | E1: Cost to Insure - Cost of Uninsured | F1: Subsidized Population | H1: Cost Avoided | I1: Cost to Insure (total) | J1: Saved Per Demo | K1: Maximum Budget | L1: Total Spending | M1: Individuals Subsidized | N1: Total saved
A2: M | 18-40 | <=138% | B2: 6367 | C2: 5135.081 | D2: 4921.7403 | E2: 213.34064 | F2: 0 | H2: =F2*C2 -> 0 | I2: =D2*F2 -> 0 | J2: =H2-I2 -> 0 | K2: 1000000 | L2: =sum(I2:I25) -> 1000000 | M2: =sum(F2:F25) -> 152.94795 | N2: =sum(J2:J25) -> 474114.28
A3: M | 18-40 | 138%-200% | B3: 4694 | C3: 4423.737 | D3: 4921.7403 | E3: -498.0033 | F3: 0 | H3: =F3*C3 -> 0 | I3: =D3*F3 -> 0 | J3: =H3-I3 -> 0
A4: M | 18-40 | 200%-250% | B4: 3642 | C4: 3930.2834 | D4: 4921.7403 | E4: -991.45692 | F4: 0 | H4: =F4*C4 -> 0 | I4: =D4*F4 -> 0 | J4: =H4-I4 -> 0
A5: M | 18-40 | 250%-400% | B5: 6659 | C5: 3330.2221 | D5: 4921.7403 | E5: -1591.5182 | F5: 0 | H5: =F5*C5 -> 0 | I5: =D5*F5 -> 0 | J5: =H5-I5 -> 0
A6: F | 18-40 | <=138% | B6: 5138 | C6: 4741.4297 | D6: 4921.7403 | E6: -180.31061 | F6: 0 | H6: =F6*C6 -> 0 | I6: =D6*F6 -> 0 | J6: =H6-I6 -> 0
A7: F | 18-40 | 138%-200% | B7: 2629 | C7: 4084.6169 | D7: 4921.7403 | E7: -837.12349 | F7: 0 | H7: =F7*C7 -> 0 | I7: =D7*F7 -> 0 | J7: =H7-I7 -> 0
A8: F | 18-40 | 200%-250% | B8: 1856 | C8: 3628.991 | D8: 4921.7403 | E8: -1292.7493 | F8: 0 | H8: =F8*C8 -> 0 | I8: =D8*F8 -> 0 | J8: =H8-I8 -> 0
A9: F | 18-40 | 250%-400% | B9: 3687 | C9: 3074.9299 | D9: 4921.7403 | E9: -1846.8104 | F9: 0 | H9: =F9*C9 -> 0 | I9: =D9*F9 -> 0 | J9: =H9-I9 -> 0
A10: M | 40-50 | <=138% | B10: 3223 | C10: 9638.0128 | D10: 6538.1721 | E10: 3099.8407 | F10: 152.94795 | H10: =F10*C10 -> 1474114.3 | I10: =D10*F10 -> 1000000 | J10: =H10-I10 -> 474114.28
A11: M | 40-50 | 138%-200% | B11: 1819 | C11: 8302.8942 | D11: 6538.1721 | E11: 1764.7221 | F11: 0 | H11: =F11*C11 -> 0 | I11: =D11*F11 -> 0 | J11: =H11-I11 -> 0
A12: M | 40-50 | 200%-250% | B12: 1479 | C12: 7376.7331 | D12: 6538.1721 | E12: 838.56102 | F12: 0 | H12: =F12*C12 -> 0 | I12: =D12*F12 -> 0 | J12: =H12-I12 -> 0
A13: M | 40-50 | 250%-400% | B13: 2193 | C13: 6250.4805 | D13: 6538.1721 | E13: -287.69157 | F13: 0 | H13: =F13*C13 -> 0 | I13: =D13*F13 -> 0 | J13: =H13-I13 -> 0
A14: F | 40-50 | <=138% | B14: 1790 | C14: 8899.1704 | D14: 6538.1721 | E14: 2360.9983 | F14: 0 | H14: =F14*C14 -> 0 | I14: =D14*F14 -> 0 | J14: =H14-I14 -> 0
... A25: F | 50-64 | 250%-400% | B25: 2022 | C25: 8095.8845 | D25: 11034.297 | E25: -2938.4128 | F25: 0 | H25: =F25*C25 -> 0 | I25: =D25*F25 -> 0 | J25: =H25-I25 -> 0
F26: 0

Sheet __OpenSolverCache__

Sheet __OpenSolver__
A1: =ModelSheet=Open Solver!A:Z -> #ERROR!
A2: =OpenSolver_AdjNum=1 -> #NAME?
A3: =OpenSolver_ChosenSolver=Google -> #NAME?
A4: =OpenSolver_FastBuild=0 -> #NAME?
A5: =OpenSolver_LinearityCheck=1 -> #NAME?
A6: =solver_adj=Open Solver!F2:F25 -> #ERROR!
A7: =solver_lhs1=Open Solver!F2:F25 -> #ERROR!
A8: =solver_lhs2=Open Solver!F2:F25 -> #ERROR!
A9: =solver_lhs3=Open Solver!L2 -> #ERROR!
A10: =solver_neg=1 -> #NAME?
A11: =solver_num=3 -> #NAME?
A12: =solver_opt=Open Solver!N2 -> #ERROR!
A13: =solver_rel1=1 -> #NAME?
A14: =solver_rel2=3 -> #NAME?
A15: =solver_rel3=1 -> #NAME?
A16: =solver_rhs1=Open Solver!B2:B25 -> #ERROR!
A17: =solver_rhs2=Open Solver!F26 -> #ERROR!
A18: =solver_rhs3=Open Solver!K2 -> #ERROR!
A19: =solver_sho=1 -> #NAME?
A20: =solver_typ=1 -> #NAME?
A21: =solver_val=0 -> #NAME?
